{
  "Table": [
    {
      "Info": {
        "RomVer": 0,
        "No": 13001,
        "DeliveryGroupID": 0,
        "Difficulty": 0,
        "Rate": 100,
        "DropTableFix": 8835426016772572659,
        "DropTableRandom": 8835426016772572659,
        "CaptureRate": 1,
        "CaptureLv": 35,
        "BossPokePara": {
          "DevId": 35,
          "FormId": 0,
          "Sex": 0,
          "Item": 0,
          "Level": 35,
          "BallId": 0,
          "WazaType": 1,
          "Waza1": {
            "WazaId": 309,
            "PointUp": 0
          },
          "Waza2": {
            "WazaId": 605,
            "PointUp": 0
          },
          "Waza3": {
            "WazaId": 227,
            "PointUp": 0
          },
          "Waza4": {
            "WazaId": 204,
            "PointUp": 0
          },
          "GemType": 1,
          "Seikaku": 0,
          "Tokusei": 1,
          "TalentType": 1,
          "TalentValue": {
            "HP": 0,
            "ATK": 0,
            "DEF": 0,
            "SPA": 0,
            "SPD": 0,
            "SPE": 0
          },
          "TalentVnum": 2,
          "EffortValue": {
            "HP": 0,
            "ATK": 0,
            "DEF": 0,
            "SPA": 0,
            "SPD": 0,
            "SPE": 0
          },
          "RareType": 0,
          "ScaleType": 0,
          "ScaleValue": 0
        },
        "BossPokeSize": {
          "HeightType": 0,
          "HeightValue": 0,
          "WeightType": 0,
          "WeightValue": 0,
          "ScaleType": 0,
          "ScaleValue": 0
        },
        "BossDesc": {
          "HpCoef": 800,
          "PowerChargeTrigerHp": 0,
          "PowerChargeTrigerTime": 0,
          "PowerChargeLimitTime": 0,
          "PowerChargeCancelDamage": 0,
          "PowerChargePenaltyTime": 0,
          "PowerChargePenaltyAction": 0,
          "PowerChargeDamageRate": 0,
          "PowerChargeGemDamageRate": 0,
          "PowerChargeChangeGemDamageRate": 0,
          "ExtraAction1": {
            "Timing": 2,
            "Action": 2,
            "Value": 50,
            "Wazano": 0
          },
          "ExtraAction2": {
            "Timing": 0,
            "Action": 0,
            "Value": 0,
            "Wazano": 0
          },
          "ExtraAction3": {
            "Timing": 0,
            "Action": 0,
            "Value": 0,
            "Wazano": 0
          },
          "ExtraAction4": {
            "Timing": 0,
            "Action": 0,
            "Value": 0,
            "Wazano": 0
          },
          "ExtraAction5": {
            "Timing": 0,
            "Action": 0,
            "Value": 0,
            "Wazano": 0
          },
          "ExtraAction6": {
            "Timing": 0,
            "Action": 0,
            "Value": 0,
            "Wazano": 0
          },
          "DoubleActionTriggerHp": 0,
          "DoubleActionTriggerTime": 0,
          "DoubleActionRate": 0
        },
        "TimeDesc": {
          "IsActive": false,
          "GameLimit": 0,
          "ClientLimit": 0,
          "CommandLimit": 0,
          "PokeReviveTime": 0,
          "AiIntervalTime": 0,
          "AiIntervalRand": 0
        }
      }
    },
    {
      "Info": {
        "RomVer": 0,
        "No": 13002,
        "DeliveryGroupID": 0,
        "Difficulty": 0,
        "Rate": 100,
        "DropTableFix": 8835428215795829081,
        "DropTableRandom": 8835428215795829081,
        "CaptureRate": 1,
        "CaptureLv": 35,
        "BossPokePara": {
          "DevId": 23,
          "FormId": 0,
          "Sex": 0,
          "Item": 0,
          "Level": 35,
          "BallId": 0,
          "WazaType": 1,
          "Waza1": {
            "WazaId": 491,
            "PointUp": 0
          },
          "Waza2": {
            "WazaId": 188,
            "PointUp": 0
          },
          "Waza3": {
            "WazaId": 389,
            "PointUp": 0
          },
          "Waza4": {
            "WazaId": 180,
            "PointUp": 0
          },
          "GemType": 1,
          "Seikaku": 0,
          "Tokusei": 1,
          "TalentType": 1,
          "TalentValue": {
            "HP": 0,
            "ATK": 0,
            "DEF": 0,
            "SPA": 0,
            "SPD": 0,
            "SPE": 0
          },
          "TalentVnum": 2,
          "EffortValue": {
            "HP": 0,
            "ATK": 0,
            "DEF": 0,
            "SPA": 0,
            "SPD": 0,
            "SPE": 0
          },
          "RareType": 0,
          "ScaleType": 0,
          "ScaleValue": 0
        },
        "BossPokeSize": {
          "HeightType": 0,
          "HeightValue": 0,
          "WeightType": 0,
          "WeightValue": 0,
          "ScaleType": 0,
          "ScaleValue": 0
        },
        "BossDesc": {
          "HpCoef": 800,
          "PowerChargeTrigerHp": 0,
          "PowerChargeTrigerTime": 0,
          "PowerChargeLimitTime": 0,
          "PowerChargeCancelDamage": 0,
          "PowerChargePenaltyTime": 0,
          "PowerChargePenaltyAction": 0,
          "PowerChargeDamageRate": 0,
          "PowerChargeGemDamageRate": 0,
          "PowerChargeChangeGemDamageRate": 0,
          "ExtraAction1": {
            "Timing": 2,
            "Action": 2,
            "Value": 50,
            "Wazano": 0
          },
          "ExtraAction2": {
            "Timing": 0,
            "Action": 0,
            "Value": 0,
            "Wazano": 0
          },
          "ExtraAction3": {
            "Timing": 0,
            "Action": 0,
            "Value": 0,
            "Wazano": 0
          },
          "ExtraAction4": {
            "Timing": 0,
            "Action": 0,
            "Value": 0,
            "Wazano": 0
          },
          "ExtraAction5": {
            "Timing": 0,
            "Action": 0,
            "Value": 0,
            "Wazano": 0
          },
          "ExtraAction6": {
            "Timing": 0,
            "Action": 0,
            "Value": 0,
            "Wazano": 0
          },
          "DoubleActionTriggerHp": 0,
          "DoubleActionTriggerTime": 0,
          "DoubleActionRate": 0
        },
        "TimeDesc": {
          "IsActive": false,
          "GameLimit": 0,
          "ClientLimit": 0,
          "CommandLimit": 0,
          "PokeReviveTime": 0,
          "AiIntervalTime": 0,
          "AiIntervalRand": 0
        }
      }
    },
    {
      "Info": {
        "RomVer": 0,
        "No": 13003,
        "DeliveryGroupID": 0,
        "Difficulty": 0,
        "Rate": 100,
        "DropTableFix": 8835424917260944448,
        "DropTableRandom": 8835424917260944448,
        "CaptureRate": 1,
        "CaptureLv": 35,
        "BossPokePara": {
          "DevId": 27,
          "FormId": 0,
          "Sex": 0,
          "Item": 0,
          "Level": 35,
          "BallId": 0,
          "WazaType": 1,
          "Waza1": {
            "WazaId": 175,
            "PointUp": 0
          },
          "Waza2": {
            "WazaId": 523,
            "PointUp": 0
          },
          "Waza3": {
            "WazaId": 163,
            "PointUp": 0
          },
          "Waza4": {
            "WazaId": 201,
            "PointUp": 0
          },
          "GemType": 1,
          "Seikaku": 0,
          "Tokusei": 1,
          "TalentType": 1,
          "TalentValue": {
            "HP": 0,
            "ATK": 0,
            "DEF": 0,
            "SPA": 0,
            "SPD": 0,
            "SPE": 0
          },
          "TalentVnum": 2,
          "EffortValue": {
            "HP": 0,
            "ATK": 0,
            "DEF": 0,
            "SPA": 0,
            "SPD": 0,
            "SPE": 0
          },
          "RareType": 0,
          "ScaleType": 0,
          "ScaleValue": 0
        },
        "BossPokeSize": {
          "HeightType": 0,
          "HeightValue": 0,
          "WeightType": 0,
          "WeightValue": 0,
          "ScaleType": 0,
          "ScaleValue": 0
        },
        "BossDesc": {
          "HpCoef": 800,
          "PowerChargeTrigerHp": 0,
          "PowerChargeTrigerTime": 0,
          "PowerChargeLimitTime": 0,
          "PowerChargeCancelDamage": 0,
          "PowerChargePenaltyTime": 0,
          "PowerChargePenaltyAction": 0,
          "PowerChargeDamageRate": 0,
          "PowerChargeGemDamageRate": 0,
          "PowerChargeChangeGemDamageRate": 0,
          "ExtraAction1": {
            "Timing": 2,
            "Action": 2,
            "Value": 50,
            "Wazano": 0
          },
          "ExtraAction2": {
            "Timing": 0,
            "Action": 0,
            "Value": 0,
            "Wazano": 0
          },
          "ExtraAction3": {
            "Timing": 0,
            "Action": 0,
            "Value": 0,
            "Wazano": 0
          },
          "ExtraAction4": {
            "Timing": 0,
            "Action": 0,
            "Value": 0,
            "Wazano": 0
          },
          "ExtraAction5": {
            "Timing": 0,
            "Action": 0,
            "Value": 0,
            "Wazano": 0
          },
          "ExtraAction6": {
            "Timing": 0,
            "Action": 0,
            "Value": 0,
            "Wazano": 0
          },
          "DoubleActionTriggerHp": 0,
          "DoubleActionTriggerTime": 0,
          "DoubleActionRate": 0
        },
        "TimeDesc": {
          "IsActive": false,
          "GameLimit": 0,
          "ClientLimit": 0,
          "CommandLimit": 0,
          "PokeReviveTime": 0,
          "AiIntervalTime": 0,
          "AiIntervalRand": 0
        }
      }
    },
    {
      "Info": {
        "RomVer": 0,
        "No": 13004,
        "DeliveryGroupID": 0,
        "Difficulty": 0,
        "Rate": 100,
        "DropTableFix": 8835429315307457292,
        "DropTableRandom": 8835429315307457292,
        "CaptureRate": 1,
        "CaptureLv": 35,
        "BossPokePara": {
          "DevId": 61,
          "FormId": 0,
          "Sex": 0,
          "Item": 0,
          "Level": 35,
          "BallId": 0,
          "WazaType": 1,
          "Waza1": {
            "WazaId": 352,
            "PointUp": 0
          },
          "Waza2": {
            "WazaId": 8,
            "PointUp": 0
          },
          "Waza3": {
            "WazaId": 34,
            "PointUp": 0
          },
          "Waza4": {
            "WazaId": 240,
            "PointUp": 0
          },
          "GemType": 1,
          "Seikaku": 0,
          "Tokusei": 1,
          "TalentType": 1,
          "TalentValue": {
            "HP": 0,
            "ATK": 0,
            "DEF": 0,
            "SPA": 0,
            "SPD": 0,
            "SPE": 0
          },
          "TalentVnum": 2,
          "EffortValue": {
            "HP": 0,
            "ATK": 0,
            "DEF": 0,
            "SPA": 0,
            "SPD": 0,
            "SPE": 0
          },
          "RareType": 0,
          "ScaleType": 0,
          "ScaleValue": 0
        },
        "BossPokeSize": {
          "HeightType": 0,
          "HeightValue": 0,
          "WeightType": 0,
          "WeightValue": 0,
          "ScaleType": 0,
          "ScaleValue": 0
        },
        "BossDesc": {
          "HpCoef": 800,
          "PowerChargeTrigerHp": 0,
          "PowerChargeTrigerTime": 0,
          "PowerChargeLimitTime": 0,
          "PowerChargeCancelDamage": 0,
          "PowerChargePenaltyTime": 0,
          "PowerChargePenaltyAction": 0,
          "PowerChargeDamageRate": 0,
          "PowerChargeGemDamageRate": 0,
          "PowerChargeChangeGemDamageRate": 0,
          "ExtraAction1": {
            "Timing": 2,
            "Action": 2,
            "Value": 50,
            "Wazano": 0
          },
          "ExtraAction2": {
            "Timing": 0,
            "Action": 0,
            "Value": 0,
            "Wazano": 0
          },
          "ExtraAction3": {
            "Timing": 0,
            "Action": 0,
            "Value": 0,
            "Wazano": 0
          },
          "ExtraAction4": {
            "Timing": 0,
            "Action": 0,
            "Value": 0,
            "Wazano": 0
          },
          "ExtraAction5": {
            "Timing": 0,
            "Action": 0,
            "Value": 0,
            "Wazano": 0
          },
          "ExtraAction6": {
            "Timing": 0,
            "Action": 0,
            "Value": 0,
            "Wazano": 0
          },
          "DoubleActionTriggerHp": 0,
          "DoubleActionTriggerTime": 0,
          "DoubleActionRate": 0
        },
        "TimeDesc": {
          "IsActive": false,
          "GameLimit": 0,
          "ClientLimit": 0,
          "CommandLimit": 0,
          "PokeReviveTime": 0,
          "AiIntervalTime": 0,
          "AiIntervalRand": 0
        }
      }
    },
    {
      "Info": {
        "RomVer": 0,
        "No": 13005,
        "DeliveryGroupID": 0,
        "Difficulty": 0,
        "Rate": 100,
        "DropTableFix": 8835428215795829081,
        "DropTableRandom": 8835428215795829081,
        "CaptureRate": 1,
        "CaptureLv": 35,
        "BossPokePara": {
          "DevId": 70,
          "FormId": 0,
          "Sex": 0,
          "Item": 0,
          "Level": 35,
          "BallId": 0,
          "WazaType": 1,
          "Waza1": {
            "WazaId": 75,
            "PointUp": 0
          },
          "Waza2": {
            "WazaId": 188,
            "PointUp": 0
          },
          "Waza3": {
            "WazaId": 230,
            "PointUp": 0
          },
          "Waza4": {
            "WazaId": 282,
            "PointUp": 0
          },
          "GemType": 1,
          "Seikaku": 0,
          "Tokusei": 1,
          "TalentType": 1,
          "TalentValue": {
            "HP": 0,
            "ATK": 0,
            "DEF": 0,
            "SPA": 0,
            "SPD": 0,
            "SPE": 0
          },
          "TalentVnum": 2,
          "EffortValue": {
            "HP": 0,
            "ATK": 0,
            "DEF": 0,
            "SPA": 0,
            "SPD": 0,
            "SPE": 0
          },
          "RareType": 0,
          "ScaleType": 0,
          "ScaleValue": 0
        },
        "BossPokeSize": {
          "HeightType": 0,
          "HeightValue": 0,
          "WeightType": 0,
          "WeightValue": 0,
          "ScaleType": 0,
          "ScaleValue": 0
        },
        "BossDesc": {
          "HpCoef": 800,
          "PowerChargeTrigerHp": 0,
          "PowerChargeTrigerTime": 0,
          "PowerChargeLimitTime": 0,
          "PowerChargeCancelDamage": 0,
          "PowerChargePenaltyTime": 0,
          "PowerChargePenaltyAction": 0,
          "PowerChargeDamageRate": 0,
          "PowerChargeGemDamageRate": 0,
          "PowerChargeChangeGemDamageRate": 0,
          "ExtraAction1": {
            "Timing": 2,
            "Action": 2,
            "Value": 50,
            "Wazano": 0
          },
          "ExtraAction2": {
            "Timing": 0,
            "Action": 0,
            "Value": 0,
            "Wazano": 0
          },
          "ExtraAction3": {
            "Timing": 0,
            "Action": 0,
            "Value": 0,
            "Wazano": 0
          },
          "ExtraAction4": {
            "Timing": 0,
            "Action": 0,
            "Value": 0,
            "Wazano": 0
          },
          "ExtraAction5": {
            "Timing": 0,
            "Action": 0,
            "Value": 0,
            "Wazano": 0
          },
          "ExtraAction6": {
            "Timing": 0,
            "Action": 0,
            "Value": 0,
            "Wazano": 0
          },
          "DoubleActionTriggerHp": 0,
          "DoubleActionTriggerTime": 0,
          "DoubleActionRate": 0
        },
        "TimeDesc": {
          "IsActive": false,
          "GameLimit": 0,
          "ClientLimit": 0,
          "CommandLimit": 0,
          "PokeReviveTime": 0,
          "AiIntervalTime": 0,
          "AiIntervalRand": 0
        }
      }
    },
    {
      "Info": {
        "RomVer": 0,
        "No": 13006,
        "DeliveryGroupID": 0,
        "Difficulty": 0,
        "Rate": 100,
        "DropTableFix": 8835426016772572659,
        "DropTableRandom": 8835426016772572659,
        "CaptureRate": 1,
        "CaptureLv": 35,
        "BossPokePara": {
          "DevId": 446,
          "FormId": 0,
          "Sex": 0,
          "Item": 0,
          "Level": 35,
          "BallId": 0,
          "WazaType": 1,
          "Waza1": {
            "WazaId": 44,
            "PointUp": 0
          },
          "Waza2": {
            "WazaId": 343,
            "PointUp": 0
          },
          "Waza3": {
            "WazaId": 175,
            "PointUp": 0
          },
          "Waza4": {
            "WazaId": 111,
            "PointUp": 0
          },
          "GemType": 1,
          "Seikaku": 0,
          "Tokusei": 1,
          "TalentType": 1,
          "TalentValue": {
            "HP": 0,
            "ATK": 0,
            "DEF": 0,
            "SPA": 0,
            "SPD": 0,
            "SPE": 0
          },
          "TalentVnum": 2,
          "EffortValue": {
            "HP": 0,
            "ATK": 0,
            "DEF": 0,
            "SPA": 0,
            "SPD": 0,
            "SPE": 0
          },
          "RareType": 0,
          "ScaleType": 0,
          "ScaleValue": 0
        },
        "BossPokeSize": {
          "HeightType": 0,
          "HeightValue": 0,
          "WeightType": 0,
          "WeightValue": 0,
          "ScaleType": 0,
          "ScaleValue": 0
        },
        "BossDesc": {
          "HpCoef": 800,
          "PowerChargeTrigerHp": 0,
          "PowerChargeTrigerTime": 0,
          "PowerChargeLimitTime": 0,
          "PowerChargeCancelDamage": 0,
          "PowerChargePenaltyTime": 0,
          "PowerChargePenaltyAction": 0,
          "PowerChargeDamageRate": 0,
          "PowerChargeGemDamageRate": 0,
          "PowerChargeChangeGemDamageRate": 0,
          "ExtraAction1": {
            "Timing": 2,
            "Action": 2,
            "Value": 50,
            "Wazano": 0
          },
          "ExtraAction2": {
            "Timing": 0,
            "Action": 0,
            "Value": 0,
            "Wazano": 0
          },
          "ExtraAction3": {
            "Timing": 0,
            "Action": 0,
            "Value": 0,
            "Wazano": 0
          },
          "ExtraAction4": {
            "Timing": 0,
            "Action": 0,
            "Value": 0,
            "Wazano": 0
          },
          "ExtraAction5": {
            "Timing": 0,
            "Action": 0,
            "Value": 0,
            "Wazano": 0
          },
          "ExtraAction6": {
            "Timing": 0,
            "Action": 0,
            "Value": 0,
            "Wazano": 0
          },
          "DoubleActionTriggerHp": 0,
          "DoubleActionTriggerTime": 0,
          "DoubleActionRate": 0
        },
        "TimeDesc": {
          "IsActive": false,
          "GameLimit": 0,
          "ClientLimit": 0,
          "CommandLimit": 0,
          "PokeReviveTime": 0,
          "AiIntervalTime": 0,
          "AiIntervalRand": 0
        }
      }
    },
    {
      "Info": {
        "RomVer": 0,
        "No": 13007,
        "DeliveryGroupID": 0,
        "Difficulty": 0,
        "Rate": 100,
        "DropTableFix": 8835429315307457292,
        "DropTableRandom": 8835429315307457292,
        "CaptureRate": 1,
        "CaptureLv": 35,
        "BossPokePara": {
          "DevId": 162,
          "FormId": 0,
          "Sex": 0,
          "Item": 0,
          "Level": 35,
          "BallId": 0,
          "WazaType": 1,
          "Waza1": {
            "WazaId": 36,
            "PointUp": 0
          },
          "Waza2": {
            "WazaId": 882,
            "PointUp": 0
          },
          "Waza3": {
            "WazaId": 116,
            "PointUp": 0
          },
          "Waza4": {
            "WazaId": 402,
            "PointUp": 0
          },
          "GemType": 1,
          "Seikaku": 0,
          "Tokusei": 1,
          "TalentType": 1,
          "TalentValue": {
            "HP": 0,
            "ATK": 0,
            "DEF": 0,
            "SPA": 0,
            "SPD": 0,
            "SPE": 0
          },
          "TalentVnum": 2,
          "EffortValue": {
            "HP": 0,
            "ATK": 0,
            "DEF": 0,
            "SPA": 0,
            "SPD": 0,
            "SPE": 0
          },
          "RareType": 0,
          "ScaleType": 0,
          "ScaleValue": 0
        },
        "BossPokeSize": {
          "HeightType": 0,
          "HeightValue": 0,
          "WeightType": 0,
          "WeightValue": 0,
          "ScaleType": 0,
          "ScaleValue": 0
        },
        "BossDesc": {
          "HpCoef": 800,
          "PowerChargeTrigerHp": 0,
          "PowerChargeTrigerTime": 0,
          "PowerChargeLimitTime": 0,
          "PowerChargeCancelDamage": 0,
          "PowerChargePenaltyTime": 0,
          "PowerChargePenaltyAction": 0,
          "PowerChargeDamageRate": 0,
          "PowerChargeGemDamageRate": 0,
          "PowerChargeChangeGemDamageRate": 0,
          "ExtraAction1": {
            "Timing": 2,
            "Action": 2,
            "Value": 50,
            "Wazano": 0
          },
          "ExtraAction2": {
            "Timing": 0,
            "Action": 0,
            "Value": 0,
            "Wazano": 0
          },
          "ExtraAction3": {
            "Timing": 0,
            "Action": 0,
            "Value": 0,
            "Wazano": 0
          },
          "ExtraAction4": {
            "Timing": 0,
            "Action": 0,
            "Value": 0,
            "Wazano": 0
          },
          "ExtraAction5": {
            "Timing": 0,
            "Action": 0,
            "Value": 0,
            "Wazano": 0
          },
          "ExtraAction6": {
            "Timing": 0,
            "Action": 0,
            "Value": 0,
            "Wazano": 0
          },
          "DoubleActionTriggerHp": 0,
          "DoubleActionTriggerTime": 0,
          "DoubleActionRate": 0
        },
        "TimeDesc": {
          "IsActive": false,
          "GameLimit": 0,
          "ClientLimit": 0,
          "CommandLimit": 0,
          "PokeReviveTime": 0,
          "AiIntervalTime": 0,
          "AiIntervalRand": 0
        }
      }
    },
    {
      "Info": {
        "RomVer": 0,
        "No": 13008,
        "DeliveryGroupID": 0,
        "Difficulty": 0,
        "Rate": 100,
        "DropTableFix": 8835432613842341925,
        "DropTableRandom": 8835432613842341925,
        "CaptureRate": 1,
        "CaptureLv": 35,
        "BossPokePara": {
          "DevId": 164,
          "FormId": 0,
          "Sex": 0,
          "Item": 0,
          "Level": 35,
          "BallId": 0,
          "WazaType": 1,
          "Waza1": {
            "WazaId": 814,
            "PointUp": 0
          },
          "Waza2": {
            "WazaId": 326,
            "PointUp": 0
          },
          "Waza3": {
            "WazaId": 403,
            "PointUp": 0
          },
          "Waza4": {
            "WazaId": 115,
            "PointUp": 0
          },
          "GemType": 1,
          "Seikaku": 0,
          "Tokusei": 1,
          "TalentType": 1,
          "TalentValue": {
            "HP": 0,
            "ATK": 0,
            "DEF": 0,
            "SPA": 0,
            "SPD": 0,
            "SPE": 0
          },
          "TalentVnum": 2,
          "EffortValue": {
            "HP": 0,
            "ATK": 0,
            "DEF": 0,
            "SPA": 0,
            "SPD": 0,
            "SPE": 0
          },
          "RareType": 0,
          "ScaleType": 0,
          "ScaleValue": 0
        },
        "BossPokeSize": {
          "HeightType": 0,
          "HeightValue": 0,
          "WeightType": 0,
          "WeightValue": 0,
          "ScaleType": 0,
          "ScaleValue": 0
        },
        "BossDesc": {
          "HpCoef": 800,
          "PowerChargeTrigerHp": 0,
          "PowerChargeTrigerTime": 0,
          "PowerChargeLimitTime": 0,
          "PowerChargeCancelDamage": 0,
          "PowerChargePenaltyTime": 0,
          "PowerChargePenaltyAction": 0,
          "PowerChargeDamageRate": 0,
          "PowerChargeGemDamageRate": 0,
          "PowerChargeChangeGemDamageRate": 0,
          "ExtraAction1": {
            "Timing": 2,
            "Action": 2,
            "Value": 50,
            "Wazano": 0
          },
          "ExtraAction2": {
            "Timing": 0,
            "Action": 0,
            "Value": 0,
            "Wazano": 0
          },
          "ExtraAction3": {
            "Timing": 0,
            "Action": 0,
            "Value": 0,
            "Wazano": 0
          },
          "ExtraAction4": {
            "Timing": 0,
            "Action": 0,
            "Value": 0,
            "Wazano": 0
          },
          "ExtraAction5": {
            "Timing": 0,
            "Action": 0,
            "Value": 0,
            "Wazano": 0
          },
          "ExtraAction6": {
            "Timing": 0,
            "Action": 0,
            "Value": 0,
            "Wazano": 0
          },
          "DoubleActionTriggerHp": 0,
          "DoubleActionTriggerTime": 0,
          "DoubleActionRate": 0
        },
        "TimeDesc": {
          "IsActive": false,
          "GameLimit": 0,
          "ClientLimit": 0,
          "CommandLimit": 0,
          "PokeReviveTime": 0,
          "AiIntervalTime": 0,
          "AiIntervalRand": 0
        }
      }
    },
    {
      "Info": {
        "RomVer": 0,
        "No": 13009,
        "DeliveryGroupID": 0,
        "Difficulty": 0,
        "Rate": 100,
        "DropTableFix": 8835428215795829081,
        "DropTableRandom": 8835428215795829081,
        "CaptureRate": 1,
        "CaptureLv": 35,
        "BossPokePara": {
          "DevId": 168,
          "FormId": 0,
          "Sex": 0,
          "Item": 0,
          "Level": 35,
          "BallId": 0,
          "WazaType": 1,
          "Waza1": {
            "WazaId": 398,
            "PointUp": 0
          },
          "Waza2": {
            "WazaId": 450,
            "PointUp": 0
          },
          "Waza3": {
            "WazaId": 425,
            "PointUp": 0
          },
          "Waza4": {
            "WazaId": 885,
            "PointUp": 0
          },
          "GemType": 1,
          "Seikaku": 0,
          "Tokusei": 1,
          "TalentType": 1,
          "TalentValue": {
            "HP": 0,
            "ATK": 0,
            "DEF": 0,
            "SPA": 0,
            "SPD": 0,
            "SPE": 0
          },
          "TalentVnum": 2,
          "EffortValue": {
            "HP": 0,
            "ATK": 0,
            "DEF": 0,
            "SPA": 0,
            "SPD": 0,
            "SPE": 0
          },
          "RareType": 0,
          "ScaleType": 0,
          "ScaleValue": 0
        },
        "BossPokeSize": {
          "HeightType": 0,
          "HeightValue": 0,
          "WeightType": 0,
          "WeightValue": 0,
          "ScaleType": 0,
          "ScaleValue": 0
        },
        "BossDesc": {
          "HpCoef": 800,
          "PowerChargeTrigerHp": 0,
          "PowerChargeTrigerTime": 0,
          "PowerChargeLimitTime": 0,
          "PowerChargeCancelDamage": 0,
          "PowerChargePenaltyTime": 0,
          "PowerChargePenaltyAction": 0,
          "PowerChargeDamageRate": 0,
          "PowerChargeGemDamageRate": 0,
          "PowerChargeChangeGemDamageRate": 0,
          "ExtraAction1": {
            "Timing": 2,
            "Action": 2,
            "Value": 50,
            "Wazano": 0
          },
          "ExtraAction2": {
            "Timing": 0,
            "Action": 0,
            "Value": 0,
            "Wazano": 0
          },
          "ExtraAction3": {
            "Timing": 0,
            "Action": 0,
            "Value": 0,
            "Wazano": 0
          },
          "ExtraAction4": {
            "Timing": 0,
            "Action": 0,
            "Value": 0,
            "Wazano": 0
          },
          "ExtraAction5": {
            "Timing": 0,
            "Action": 0,
            "Value": 0,
            "Wazano": 0
          },
          "ExtraAction6": {
            "Timing": 0,
            "Action": 0,
            "Value": 0,
            "Wazano": 0
          },
          "DoubleActionTriggerHp": 0,
          "DoubleActionTriggerTime": 0,
          "DoubleActionRate": 0
        },
        "TimeDesc": {
          "IsActive": false,
          "GameLimit": 0,
          "ClientLimit": 0,
          "CommandLimit": 0,
          "PokeReviveTime": 0,
          "AiIntervalTime": 0,
          "AiIntervalRand": 0
        }
      }
    },
    {
      "Info": {
        "RomVer": 1,
        "No": 13010,
        "DeliveryGroupID": 0,
        "Difficulty": 0,
        "Rate": 100,
        "DropTableFix": 8835424917260944448,
        "DropTableRandom": 8835424917260944448,
        "CaptureRate": 1,
        "CaptureLv": 35,
        "BossPokePara": {
          "DevId": 207,
          "FormId": 0,
          "Sex": 0,
          "Item": 0,
          "Level": 35,
          "BallId": 0,
          "WazaType": 1,
          "Waza1": {
            "WazaId": 342,
            "PointUp": 0
          },
          "Waza2": {
            "WazaId": 163,
            "PointUp": 0
          },
          "Waza3": {
            "WazaId": 404,
            "PointUp": 0
          },
          "Waza4": {
            "WazaId": 364,
            "PointUp": 0
          },
          "GemType": 1,
          "Seikaku": 0,
          "Tokusei": 1,
          "TalentType": 1,
          "TalentValue": {
            "HP": 0,
            "ATK": 0,
            "DEF": 0,
            "SPA": 0,
            "SPD": 0,
            "SPE": 0
          },
          "TalentVnum": 2,
          "EffortValue": {
            "HP": 0,
            "ATK": 0,
            "DEF": 0,
            "SPA": 0,
            "SPD": 0,
            "SPE": 0
          },
          "RareType": 0,
          "ScaleType": 0,
          "ScaleValue": 0
        },
        "BossPokeSize": {
          "HeightType": 0,
          "HeightValue": 0,
          "WeightType": 0,
          "WeightValue": 0,
          "ScaleType": 0,
          "ScaleValue": 0
        },
        "BossDesc": {
          "HpCoef": 800,
          "PowerChargeTrigerHp": 0,
          "PowerChargeTrigerTime": 0,
          "PowerChargeLimitTime": 0,
          "PowerChargeCancelDamage": 0,
          "PowerChargePenaltyTime": 0,
          "PowerChargePenaltyAction": 0,
          "PowerChargeDamageRate": 0,
          "PowerChargeGemDamageRate": 0,
          "PowerChargeChangeGemDamageRate": 0,
          "ExtraAction1": {
            "Timing": 2,
            "Action": 2,
            "Value": 50,
            "Wazano": 0
          },
          "ExtraAction2": {
            "Timing": 0,
            "Action": 0,
            "Value": 0,
            "Wazano": 0
          },
          "ExtraAction3": {
            "Timing": 0,
            "Action": 0,
            "Value": 0,
            "Wazano": 0
          },
          "ExtraAction4": {
            "Timing": 0,
            "Action": 0,
            "Value": 0,
            "Wazano": 0
          },
          "ExtraAction5": {
            "Timing": 0,
            "Action": 0,
            "Value": 0,
            "Wazano": 0
          },
          "ExtraAction6": {
            "Timing": 0,
            "Action": 0,
            "Value": 0,
            "Wazano": 0
          },
          "DoubleActionTriggerHp": 0,
          "DoubleActionTriggerTime": 0,
          "DoubleActionRate": 0
        },
        "TimeDesc": {
          "IsActive": false,
          "GameLimit": 0,
          "ClientLimit": 0,
          "CommandLimit": 0,
          "PokeReviveTime": 0,
          "AiIntervalTime": 0,
          "AiIntervalRand": 0
        }
      }
    },
    {
      "Info": {
        "RomVer": 0,
        "No": 13011,
        "DeliveryGroupID": 0,
        "Difficulty": 0,
        "Rate": 100,
        "DropTableFix": 8835432613842341925,
        "DropTableRandom": 8835432613842341925,
        "CaptureRate": 1,
        "CaptureLv": 35,
        "BossPokePara": {
          "DevId": 271,
          "FormId": 0,
          "Sex": 0,
          "Item": 0,
          "Level": 35,
          "BallId": 0,
          "WazaType": 1,
          "Waza1": {
            "WazaId": 75,
            "PointUp": 0
          },
          "Waza2": {
            "WazaId": 352,
            "PointUp": 0
          },
          "Waza3": {
            "WazaId": 886,
            "PointUp": 0
          },
          "Waza4": {
            "WazaId": 252,
            "PointUp": 0
          },
          "GemType": 1,
          "Seikaku": 0,
          "Tokusei": 1,
          "TalentType": 1,
          "TalentValue": {
            "HP": 0,
            "ATK": 0,
            "DEF": 0,
            "SPA": 0,
            "SPD": 0,
            "SPE": 0
          },
          "TalentVnum": 2,
          "EffortValue": {
            "HP": 0,
            "ATK": 0,
            "DEF": 0,
            "SPA": 0,
            "SPD": 0,
            "SPE": 0
          },
          "RareType": 0,
          "ScaleType": 0,
          "ScaleValue": 0
        },
        "BossPokeSize": {
          "HeightType": 0,
          "HeightValue": 0,
          "WeightType": 0,
          "WeightValue": 0,
          "ScaleType": 0,
          "ScaleValue": 0
        },
        "BossDesc": {
          "HpCoef": 800,
          "PowerChargeTrigerHp": 0,
          "PowerChargeTrigerTime": 0,
          "PowerChargeLimitTime": 0,
          "PowerChargeCancelDamage": 0,
          "PowerChargePenaltyTime": 0,
          "PowerChargePenaltyAction": 0,
          "PowerChargeDamageRate": 0,
          "PowerChargeGemDamageRate": 0,
          "PowerChargeChangeGemDamageRate": 0,
          "ExtraAction1": {
            "Timing": 2,
            "Action": 2,
            "Value": 50,
            "Wazano": 0
          },
          "ExtraAction2": {
            "Timing": 0,
            "Action": 0,
            "Value": 0,
            "Wazano": 0
          },
          "ExtraAction3": {
            "Timing": 0,
            "Action": 0,
            "Value": 0,
            "Wazano": 0
          },
          "ExtraAction4": {
            "Timing": 0,
            "Action": 0,
            "Value": 0,
            "Wazano": 0
          },
          "ExtraAction5": {
            "Timing": 0,
            "Action": 0,
            "Value": 0,
            "Wazano": 0
          },
          "ExtraAction6": {
            "Timing": 0,
            "Action": 0,
            "Value": 0,
            "Wazano": 0
          },
          "DoubleActionTriggerHp": 0,
          "DoubleActionTriggerTime": 0,
          "DoubleActionRate": 0
        },
        "TimeDesc": {
          "IsActive": false,
          "GameLimit": 0,
          "ClientLimit": 0,
          "CommandLimit": 0,
          "PokeReviveTime": 0,
          "AiIntervalTime": 0,
          "AiIntervalRand": 0
        }
      }
    },
    {
      "Info": {
        "RomVer": 0,
        "No": 13012,
        "DeliveryGroupID": 0,
        "Difficulty": 0,
        "Rate": 100,
        "DropTableFix": 8835428215795829081,
        "DropTableRandom": 8835428215795829081,
        "CaptureRate": 1,
        "CaptureLv": 35,
        "BossPokePara": {
          "DevId": 274,
          "FormId": 0,
          "Sex": 0,
          "Item": 0,
          "Level": 35,
          "BallId": 0,
          "WazaType": 1,
          "Waza1": {
            "WazaId": 75,
            "PointUp": 0
          },
          "Waza2": {
            "WazaId": 36,
            "PointUp": 0
          },
          "Waza3": {
            "WazaId": 252,
            "PointUp": 0
          },
          "Waza4": {
            "WazaId": 371,
            "PointUp": 0
          },
          "GemType": 1,
          "Seikaku": 0,
          "Tokusei": 1,
          "TalentType": 1,
          "TalentValue": {
            "HP": 0,
            "ATK": 0,
            "DEF": 0,
            "SPA": 0,
            "SPD": 0,
            "SPE": 0
          },
          "TalentVnum": 2,
          "EffortValue": {
            "HP": 0,
            "ATK": 0,
            "DEF": 0,
            "SPA": 0,
            "SPD": 0,
            "SPE": 0
          },
          "RareType": 0,
          "ScaleType": 0,
          "ScaleValue": 0
        },
        "BossPokeSize": {
          "HeightType": 0,
          "HeightValue": 0,
          "WeightType": 0,
          "WeightValue": 0,
          "ScaleType": 0,
          "ScaleValue": 0
        },
        "BossDesc": {
          "HpCoef": 800,
          "PowerChargeTrigerHp": 0,
          "PowerChargeTrigerTime": 0,
          "PowerChargeLimitTime": 0,
          "PowerChargeCancelDamage": 0,
          "PowerChargePenaltyTime": 0,
          "PowerChargePenaltyAction": 0,
          "PowerChargeDamageRate": 0,
          "PowerChargeGemDamageRate": 0,
          "PowerChargeChangeGemDamageRate": 0,
          "ExtraAction1": {
            "Timing": 2,
            "Action": 2,
            "Value": 50,
            "Wazano": 0
          },
          "ExtraAction2": {
            "Timing": 0,
            "Action": 0,
            "Value": 0,
            "Wazano": 0
          },
          "ExtraAction3": {
            "Timing": 0,
            "Action": 0,
            "Value": 0,
            "Wazano": 0
          },
          "ExtraAction4": {
            "Timing": 0,
            "Action": 0,
            "Value": 0,
            "Wazano": 0
          },
          "ExtraAction5": {
            "Timing": 0,
            "Action": 0,
            "Value": 0,
            "Wazano": 0
          },
          "ExtraAction6": {
            "Timing": 0,
            "Action": 0,
            "Value": 0,
            "Wazano": 0
          },
          "DoubleActionTriggerHp": 0,
          "DoubleActionTriggerTime": 0,
          "DoubleActionRate": 0
        },
        "TimeDesc": {
          "IsActive": false,
          "GameLimit": 0,
          "ClientLimit": 0,
          "CommandLimit": 0,
          "PokeReviveTime": 0,
          "AiIntervalTime": 0,
          "AiIntervalRand": 0
        }
      }
    },
    {
      "Info": {
        "RomVer": 0,
        "No": 13013,
        "DeliveryGroupID": 0,
        "Difficulty": 0,
        "Rate": 100,
        "DropTableFix": 8835424917260944448,
        "DropTableRandom": 8835424917260944448,
        "CaptureRate": 1,
        "CaptureLv": 35,
        "BossPokePara": {
          "DevId": 299,
          "FormId": 0,
          "Sex": 0,
          "Item": 0,
          "Level": 35,
          "BallId": 0,
          "WazaType": 1,
          "Waza1": {
            "WazaId": 317,
            "PointUp": 0
          },
          "Waza2": {
            "WazaId": 86,
            "PointUp": 0
          },
          "Waza3": {
            "WazaId": 209,
            "PointUp": 0
          },
          "Waza4": {
            "WazaId": 408,
            "PointUp": 0
          },
          "GemType": 1,
          "Seikaku": 0,
          "Tokusei": 1,
          "TalentType": 1,
          "TalentValue": {
            "HP": 0,
            "ATK": 0,
            "DEF": 0,
            "SPA": 0,
            "SPD": 0,
            "SPE": 0
          },
          "TalentVnum": 2,
          "EffortValue": {
            "HP": 0,
            "ATK": 0,
            "DEF": 0,
            "SPA": 0,
            "SPD": 0,
            "SPE": 0
          },
          "RareType": 0,
          "ScaleType": 0,
          "ScaleValue": 0
        },
        "BossPokeSize": {
          "HeightType": 0,
          "HeightValue": 0,
          "WeightType": 0,
          "WeightValue": 0,
          "ScaleType": 0,
          "ScaleValue": 0
        },
        "BossDesc": {
          "HpCoef": 800,
          "PowerChargeTrigerHp": 0,
          "PowerChargeTrigerTime": 0,
          "PowerChargeLimitTime": 0,
          "PowerChargeCancelDamage": 0,
          "PowerChargePenaltyTime": 0,
          "PowerChargePenaltyAction": 0,
          "PowerChargeDamageRate": 0,
          "PowerChargeGemDamageRate": 0,
          "PowerChargeChangeGemDamageRate": 0,
          "ExtraAction1": {
            "Timing": 2,
            "Action": 2,
            "Value": 50,
            "Wazano": 0
          },
          "ExtraAction2": {
            "Timing": 0,
            "Action": 0,
            "Value": 0,
            "Wazano": 0
          },
          "ExtraAction3": {
            "Timing": 0,
            "Action": 0,
            "Value": 0,
            "Wazano": 0
          },
          "ExtraAction4": {
            "Timing": 0,
            "Action": 0,
            "Value": 0,
            "Wazano": 0
          },
          "ExtraAction5": {
            "Timing": 0,
            "Action": 0,
            "Value": 0,
            "Wazano": 0
          },
          "ExtraAction6": {
            "Timing": 0,
            "Action": 0,
            "Value": 0,
            "Wazano": 0
          },
          "DoubleActionTriggerHp": 0,
          "DoubleActionTriggerTime": 0,
          "DoubleActionRate": 0
        },
        "TimeDesc": {
          "IsActive": false,
          "GameLimit": 0,
          "ClientLimit": 0,
          "CommandLimit": 0,
          "PokeReviveTime": 0,
          "AiIntervalTime": 0,
          "AiIntervalRand": 0
        }
      }
    },
    {
      "Info": {
        "RomVer": 0,
        "No": 13014,
        "DeliveryGroupID": 0,
        "Difficulty": 0,
        "Rate": 100,
        "DropTableFix": 8835429315307457292,
        "DropTableRandom": 8835429315307457292,
        "CaptureRate": 1,
        "CaptureLv": 35,
        "BossPokePara": {
          "DevId": 349,
          "FormId": 0,
          "Sex": 0,
          "Item": 0,
          "Level": 35,
          "BallId": 0,
          "WazaType": 1,
          "Waza1": {
            "WazaId": 33,
            "PointUp": 0
          },
          "Waza2": {
            "WazaId": 175,
            "PointUp": 0
          },
          "Waza3": {
            "WazaId": 150,
            "PointUp": 0
          },
          "Waza4": {
            "WazaId": 114,
            "PointUp": 0
          },
          "GemType": 1,
          "Seikaku": 0,
          "Tokusei": 1,
          "TalentType": 1,
          "TalentValue": {
            "HP": 0,
            "ATK": 0,
            "DEF": 0,
            "SPA": 0,
            "SPD": 0,
            "SPE": 0
          },
          "TalentVnum": 2,
          "EffortValue": {
            "HP": 0,
            "ATK": 0,
            "DEF": 0,
            "SPA": 0,
            "SPD": 0,
            "SPE": 0
          },
          "RareType": 0,
          "ScaleType": 0,
          "ScaleValue": 0
        },
        "BossPokeSize": {
          "HeightType": 0,
          "HeightValue": 0,
          "WeightType": 0,
          "WeightValue": 0,
          "ScaleType": 0,
          "ScaleValue": 0
        },
        "BossDesc": {
          "HpCoef": 800,
          "PowerChargeTrigerHp": 0,
          "PowerChargeTrigerTime": 0,
          "PowerChargeLimitTime": 0,
          "PowerChargeCancelDamage": 0,
          "PowerChargePenaltyTime": 0,
          "PowerChargePenaltyAction": 0,
          "PowerChargeDamageRate": 0,
          "PowerChargeGemDamageRate": 0,
          "PowerChargeChangeGemDamageRate": 0,
          "ExtraAction1": {
            "Timing": 2,
            "Action": 2,
            "Value": 50,
            "Wazano": 0
          },
          "ExtraAction2": {
            "Timing": 0,
            "Action": 0,
            "Value": 0,
            "Wazano": 0
          },
          "ExtraAction3": {
            "Timing": 0,
            "Action": 0,
            "Value": 0,
            "Wazano": 0
          },
          "ExtraAction4": {
            "Timing": 0,
            "Action": 0,
            "Value": 0,
            "Wazano": 0
          },
          "ExtraAction5": {
            "Timing": 0,
            "Action": 0,
            "Value": 0,
            "Wazano": 0
          },
          "ExtraAction6": {
            "Timing": 0,
            "Action": 0,
            "Value": 0,
            "Wazano": 0
          },
          "DoubleActionTriggerHp": 0,
          "DoubleActionTriggerTime": 0,
          "DoubleActionRate": 0
        },
        "TimeDesc": {
          "IsActive": false,
          "GameLimit": 0,
          "ClientLimit": 0,
          "CommandLimit": 0,
          "PokeReviveTime": 0,
          "AiIntervalTime": 0,
          "AiIntervalRand": 0
        }
      }
    },
    {
      "Info": {
        "RomVer": 0,
        "No": 13015,
        "DeliveryGroupID": 0,
        "Difficulty": 0,
        "Rate": 100,
        "DropTableFix": 8835431514330713714,
        "DropTableRandom": 8835431514330713714,
        "CaptureRate": 1,
        "CaptureLv": 35,
        "BossPokePara": {
          "DevId": 433,
          "FormId": 0,
          "Sex": 0,
          "Item": 0,
          "Level": 35,
          "BallId": 0,
          "WazaType": 1,
          "Waza1": {
            "WazaId": 93,
            "PointUp": 0
          },
          "Waza2": {
            "WazaId": 281,
            "PointUp": 0
          },
          "Waza3": {
            "WazaId": 387,
            "PointUp": 0
          },
          "Waza4": {
            "WazaId": 253,
            "PointUp": 0
          },
          "GemType": 1,
          "Seikaku": 0,
          "Tokusei": 1,
          "TalentType": 1,
          "TalentValue": {
            "HP": 0,
            "ATK": 0,
            "DEF": 0,
            "SPA": 0,
            "SPD": 0,
            "SPE": 0
          },
          "TalentVnum": 2,
          "EffortValue": {
            "HP": 0,
            "ATK": 0,
            "DEF": 0,
            "SPA": 0,
            "SPD": 0,
            "SPE": 0
          },
          "RareType": 0,
          "ScaleType": 0,
          "ScaleValue": 0
        },
        "BossPokeSize": {
          "HeightType": 0,
          "HeightValue": 0,
          "WeightType": 0,
          "WeightValue": 0,
          "ScaleType": 0,
          "ScaleValue": 0
        },
        "BossDesc": {
          "HpCoef": 800,
          "PowerChargeTrigerHp": 0,
          "PowerChargeTrigerTime": 0,
          "PowerChargeLimitTime": 0,
          "PowerChargeCancelDamage": 0,
          "PowerChargePenaltyTime": 0,
          "PowerChargePenaltyAction": 0,
          "PowerChargeDamageRate": 0,
          "PowerChargeGemDamageRate": 0,
          "PowerChargeChangeGemDamageRate": 0,
          "ExtraAction1": {
            "Timing": 2,
            "Action": 2,
            "Value": 50,
            "Wazano": 0
          },
          "ExtraAction2": {
            "Timing": 0,
            "Action": 0,
            "Value": 0,
            "Wazano": 0
          },
          "ExtraAction3": {
            "Timing": 0,
            "Action": 0,
            "Value": 0,
            "Wazano": 0
          },
          "ExtraAction4": {
            "Timing": 0,
            "Action": 0,
            "Value": 0,
            "Wazano": 0
          },
          "ExtraAction5": {
            "Timing": 0,
            "Action": 0,
            "Value": 0,
            "Wazano": 0
          },
          "ExtraAction6": {
            "Timing": 0,
            "Action": 0,
            "Value": 0,
            "Wazano": 0
          },
          "DoubleActionTriggerHp": 0,
          "DoubleActionTriggerTime": 0,
          "DoubleActionRate": 0
        },
        "TimeDesc": {
          "IsActive": false,
          "GameLimit": 0,
          "ClientLimit": 0,
          "CommandLimit": 0,
          "PokeReviveTime": 0,
          "AiIntervalTime": 0,
          "AiIntervalRand": 0
        }
      }
    },
    {
      "Info": {
        "RomVer": 0,
        "No": 13016,
        "DeliveryGroupID": 0,
        "Difficulty": 0,
        "Rate": 100,
        "DropTableFix": 8835428215795829081,
        "DropTableRandom": 8835428215795829081,
        "CaptureRate": 1,
        "CaptureLv": 35,
        "BossPokePara": {
          "DevId": 533,
          "FormId": 0,
          "Sex": 0,
          "Item": 0,
          "Level": 35,
          "BallId": 0,
          "WazaType": 1,
          "Waza1": {
            "WazaId": 67,
            "PointUp": 0
          },
          "Waza2": {
            "WazaId": 157,
            "PointUp": 0
          },
          "Waza3": {
            "WazaId": 184,
            "PointUp": 0
          },
          "Waza4": {
            "WazaId": 21,
            "PointUp": 0
          },
          "GemType": 1,
          "Seikaku": 0,
          "Tokusei": 1,
          "TalentType": 1,
          "TalentValue": {
            "HP": 0,
            "ATK": 0,
            "DEF": 0,
            "SPA": 0,
            "SPD": 0,
            "SPE": 0
          },
          "TalentVnum": 2,
          "EffortValue": {
            "HP": 0,
            "ATK": 0,
            "DEF": 0,
            "SPA": 0,
            "SPD": 0,
            "SPE": 0
          },
          "RareType": 0,
          "ScaleType": 0,
          "ScaleValue": 0
        },
        "BossPokeSize": {
          "HeightType": 0,
          "HeightValue": 0,
          "WeightType": 0,
          "WeightValue": 0,
          "ScaleType": 0,
          "ScaleValue": 0
        },
        "BossDesc": {
          "HpCoef": 800,
          "PowerChargeTrigerHp": 0,
          "PowerChargeTrigerTime": 0,
          "PowerChargeLimitTime": 0,
          "PowerChargeCancelDamage": 0,
          "PowerChargePenaltyTime": 0,
          "PowerChargePenaltyAction": 0,
          "PowerChargeDamageRate": 0,
          "PowerChargeGemDamageRate": 0,
          "PowerChargeChangeGemDamageRate": 0,
          "ExtraAction1": {
            "Timing": 2,
            "Action": 2,
            "Value": 50,
            "Wazano": 0
          },
          "ExtraAction2": {
            "Timing": 0,
            "Action": 0,
            "Value": 0,
            "Wazano": 0
          },
          "ExtraAction3": {
            "Timing": 0,
            "Action": 0,
            "Value": 0,
            "Wazano": 0
          },
          "ExtraAction4": {
            "Timing": 0,
            "Action": 0,
            "Value": 0,
            "Wazano": 0
          },
          "ExtraAction5": {
            "Timing": 0,
            "Action": 0,
            "Value": 0,
            "Wazano": 0
          },
          "ExtraAction6": {
            "Timing": 0,
            "Action": 0,
            "Value": 0,
            "Wazano": 0
          },
          "DoubleActionTriggerHp": 0,
          "DoubleActionTriggerTime": 0,
          "DoubleActionRate": 0
        },
        "TimeDesc": {
          "IsActive": false,
          "GameLimit": 0,
          "ClientLimit": 0,
          "CommandLimit": 0,
          "PokeReviveTime": 0,
          "AiIntervalTime": 0,
          "AiIntervalRand": 0
        }
      }
    },
    {
      "Info": {
        "RomVer": 0,
        "No": 13017,
        "DeliveryGroupID": 0,
        "Difficulty": 0,
        "Rate": 100,
        "DropTableFix": 8835424917260944448,
        "DropTableRandom": 8835424917260944448,
        "CaptureRate": 1,
        "CaptureLv": 35,
        "BossPokePara": {
          "DevId": 541,
          "FormId": 0,
          "Sex": 0,
          "Item": 0,
          "Level": 35,
          "BallId": 0,
          "WazaType": 1,
          "Waza1": {
            "WazaId": 522,
            "PointUp": 0
          },
          "Waza2": {
            "WazaId": 75,
            "PointUp": 0
          },
          "Waza3": {
            "WazaId": 81,
            "PointUp": 0
          },
          "Waza4": {
            "WazaId": 450,
            "PointUp": 0
          },
          "GemType": 1,
          "Seikaku": 0,
          "Tokusei": 1,
          "TalentType": 1,
          "TalentValue": {
            "HP": 0,
            "ATK": 0,
            "DEF": 0,
            "SPA": 0,
            "SPD": 0,
            "SPE": 0
          },
          "TalentVnum": 2,
          "EffortValue": {
            "HP": 0,
            "ATK": 0,
            "DEF": 0,
            "SPA": 0,
            "SPD": 0,
            "SPE": 0
          },
          "RareType": 0,
          "ScaleType": 0,
          "ScaleValue": 0
        },
        "BossPokeSize": {
          "HeightType": 0,
          "HeightValue": 0,
          "WeightType": 0,
          "WeightValue": 0,
          "ScaleType": 0,
          "ScaleValue": 0
        },
        "BossDesc": {
          "HpCoef": 800,
          "PowerChargeTrigerHp": 0,
          "PowerChargeTrigerTime": 0,
          "PowerChargeLimitTime": 0,
          "PowerChargeCancelDamage": 0,
          "PowerChargePenaltyTime": 0,
          "PowerChargePenaltyAction": 0,
          "PowerChargeDamageRate": 0,
          "PowerChargeGemDamageRate": 0,
          "PowerChargeChangeGemDamageRate": 0,
          "ExtraAction1": {
            "Timing": 2,
            "Action": 2,
            "Value": 50,
            "Wazano": 0
          },
          "ExtraAction2": {
            "Timing": 0,
            "Action": 0,
            "Value": 0,
            "Wazano": 0
          },
          "ExtraAction3": {
            "Timing": 0,
            "Action": 0,
            "Value": 0,
            "Wazano": 0
          },
          "ExtraAction4": {
            "Timing": 0,
            "Action": 0,
            "Value": 0,
            "Wazano": 0
          },
          "ExtraAction5": {
            "Timing": 0,
            "Action": 0,
            "Value": 0,
            "Wazano": 0
          },
          "ExtraAction6": {
            "Timing": 0,
            "Action": 0,
            "Value": 0,
            "Wazano": 0
          },
          "DoubleActionTriggerHp": 0,
          "DoubleActionTriggerTime": 0,
          "DoubleActionRate": 0
        },
        "TimeDesc": {
          "IsActive": false,
          "GameLimit": 0,
          "ClientLimit": 0,
          "CommandLimit": 0,
          "PokeReviveTime": 0,
          "AiIntervalTime": 0,
          "AiIntervalRand": 0
        }
      }
    },
    {
      "Info": {
        "RomVer": 0,
        "No": 13018,
        "DeliveryGroupID": 0,
        "Difficulty": 0,
        "Rate": 100,
        "DropTableFix": 8835428215795829081,
        "DropTableRandom": 8835428215795829081,
        "CaptureRate": 1,
        "CaptureLv": 35,
        "BossPokePara": {
          "DevId": 619,
          "FormId": 0,
          "Sex": 0,
          "Item": 0,
          "Level": 35,
          "BallId": 0,
          "WazaType": 1,
          "Waza1": {
            "WazaId": 395,
            "PointUp": 0
          },
          "Waza2": {
            "WazaId": 252,
            "PointUp": 0
          },
          "Waza3": {
            "WazaId": 282,
            "PointUp": 0
          },
          "Waza4": {
            "WazaId": 364,
            "PointUp": 0
          },
          "GemType": 1,
          "Seikaku": 0,
          "Tokusei": 1,
          "TalentType": 1,
          "TalentValue": {
            "HP": 0,
            "ATK": 0,
            "DEF": 0,
            "SPA": 0,
            "SPD": 0,
            "SPE": 0
          },
          "TalentVnum": 2,
          "EffortValue": {
            "HP": 0,
            "ATK": 0,
            "DEF": 0,
            "SPA": 0,
            "SPD": 0,
            "SPE": 0
          },
          "RareType": 0,
          "ScaleType": 0,
          "ScaleValue": 0
        },
        "BossPokeSize": {
          "HeightType": 0,
          "HeightValue": 0,
          "WeightType": 0,
          "WeightValue": 0,
          "ScaleType": 0,
          "ScaleValue": 0
        },
        "BossDesc": {
          "HpCoef": 800,
          "PowerChargeTrigerHp": 0,
          "PowerChargeTrigerTime": 0,
          "PowerChargeLimitTime": 0,
          "PowerChargeCancelDamage": 0,
          "PowerChargePenaltyTime": 0,
          "PowerChargePenaltyAction": 0,
          "PowerChargeDamageRate": 0,
          "PowerChargeGemDamageRate": 0,
          "PowerChargeChangeGemDamageRate": 0,
          "ExtraAction1": {
            "Timing": 2,
            "Action": 2,
            "Value": 50,
            "Wazano": 0
          },
          "ExtraAction2": {
            "Timing": 0,
            "Action": 0,
            "Value": 0,
            "Wazano": 0
          },
          "ExtraAction3": {
            "Timing": 0,
            "Action": 0,
            "Value": 0,
            "Wazano": 0
          },
          "ExtraAction4": {
            "Timing": 0,
            "Action": 0,
            "Value": 0,
            "Wazano": 0
          },
          "ExtraAction5": {
            "Timing": 0,
            "Action": 0,
            "Value": 0,
            "Wazano": 0
          },
          "ExtraAction6": {
            "Timing": 0,
            "Action": 0,
            "Value": 0,
            "Wazano": 0
          },
          "DoubleActionTriggerHp": 0,
          "DoubleActionTriggerTime": 0,
          "DoubleActionRate": 0
        },
        "TimeDesc": {
          "IsActive": false,
          "GameLimit": 0,
          "ClientLimit": 0,
          "CommandLimit": 0,
          "PokeReviveTime": 0,
          "AiIntervalTime": 0,
          "AiIntervalRand": 0
        }
      }
    },
    {
      "Info": {
        "RomVer": 0,
        "No": 13019,
        "DeliveryGroupID": 0,
        "Difficulty": 0,
        "Rate": 100,
        "DropTableFix": 8835424917260944448,
        "DropTableRandom": 8835424917260944448,
        "CaptureRate": 1,
        "CaptureLv": 35,
        "BossPokePara": {
          "DevId": 629,
          "FormId": 0,
          "Sex": 0,
          "Item": 0,
          "Level": 35,
          "BallId": 0,
          "WazaType": 1,
          "Waza1": {
            "WazaId": 365,
            "PointUp": 0
          },
          "Waza2": {
            "WazaId": 282,
            "PointUp": 0
          },
          "Waza3": {
            "WazaId": 492,
            "PointUp": 0
          },
          "Waza4": {
            "WazaId": 36,
            "PointUp": 0
          },
          "GemType": 1,
          "Seikaku": 0,
          "Tokusei": 1,
          "TalentType": 1,
          "TalentValue": {
            "HP": 0,
            "ATK": 0,
            "DEF": 0,
            "SPA": 0,
            "SPD": 0,
            "SPE": 0
          },
          "TalentVnum": 2,
          "EffortValue": {
            "HP": 0,
            "ATK": 0,
            "DEF": 0,
            "SPA": 0,
            "SPD": 0,
            "SPE": 0
          },
          "RareType": 0,
          "ScaleType": 0,
          "ScaleValue": 0
        },
        "BossPokeSize": {
          "HeightType": 0,
          "HeightValue": 0,
          "WeightType": 0,
          "WeightValue": 0,
          "ScaleType": 0,
          "ScaleValue": 0
        },
        "BossDesc": {
          "HpCoef": 800,
          "PowerChargeTrigerHp": 0,
          "PowerChargeTrigerTime": 0,
          "PowerChargeLimitTime": 0,
          "PowerChargeCancelDamage": 0,
          "PowerChargePenaltyTime": 0,
          "PowerChargePenaltyAction": 0,
          "PowerChargeDamageRate": 0,
          "PowerChargeGemDamageRate": 0,
          "PowerChargeChangeGemDamageRate": 0,
          "ExtraAction1": {
            "Timing": 2,
            "Action": 2,
            "Value": 50,
            "Wazano": 0
          },
          "ExtraAction2": {
            "Timing": 0,
            "Action": 0,
            "Value": 0,
            "Wazano": 0
          },
          "ExtraAction3": {
            "Timing": 0,
            "Action": 0,
            "Value": 0,
            "Wazano": 0
          },
          "ExtraAction4": {
            "Timing": 0,
            "Action": 0,
            "Value": 0,
            "Wazano": 0
          },
          "ExtraAction5": {
            "Timing": 0,
            "Action": 0,
            "Value": 0,
            "Wazano": 0
          },
          "ExtraAction6": {
            "Timing": 0,
            "Action": 0,
            "Value": 0,
            "Wazano": 0
          },
          "DoubleActionTriggerHp": 0,
          "DoubleActionTriggerTime": 0,
          "DoubleActionRate": 0
        },
        "TimeDesc": {
          "IsActive": false,
          "GameLimit": 0,
          "ClientLimit": 0,
          "CommandLimit": 0,
          "PokeReviveTime": 0,
          "AiIntervalTime": 0,
          "AiIntervalRand": 0
        }
      }
    },
    {
      "Info": {
        "RomVer": 0,
        "No": 13020,
        "DeliveryGroupID": 0,
        "Difficulty": 0,
        "Rate": 100,
        "DropTableFix": 8835424917260944448,
        "DropTableRandom": 8835424917260944448,
        "CaptureRate": 1,
        "CaptureLv": 35,
        "BossPokePara": {
          "DevId": 708,
          "FormId": 0,
          "Sex": 0,
          "Item": 0,
          "Level": 35,
          "BallId": 0,
          "WazaType": 1,
          "Waza1": {
            "WazaId": 532,
            "PointUp": 0
          },
          "Waza2": {
            "WazaId": 174,
            "PointUp": 0
          },
          "Waza3": {
            "WazaId": 389,
            "PointUp": 0
          },
          "Waza4": {
            "WazaId": 566,
            "PointUp": 0
          },
          "GemType": 1,
          "Seikaku": 0,
          "Tokusei": 1,
          "TalentType": 1,
          "TalentValue": {
            "HP": 0,
            "ATK": 0,
            "DEF": 0,
            "SPA": 0,
            "SPD": 0,
            "SPE": 0
          },
          "TalentVnum": 2,
          "EffortValue": {
            "HP": 0,
            "ATK": 0,
            "DEF": 0,
            "SPA": 0,
            "SPD": 0,
            "SPE": 0
          },
          "RareType": 0,
          "ScaleType": 0,
          "ScaleValue": 0
        },
        "BossPokeSize": {
          "HeightType": 0,
          "HeightValue": 0,
          "WeightType": 0,
          "WeightValue": 0,
          "ScaleType": 0,
          "ScaleValue": 0
        },
        "BossDesc": {
          "HpCoef": 800,
          "PowerChargeTrigerHp": 0,
          "PowerChargeTrigerTime": 0,
          "PowerChargeLimitTime": 0,
          "PowerChargeCancelDamage": 0,
          "PowerChargePenaltyTime": 0,
          "PowerChargePenaltyAction": 0,
          "PowerChargeDamageRate": 0,
          "PowerChargeGemDamageRate": 0,
          "PowerChargeChangeGemDamageRate": 0,
          "ExtraAction1": {
            "Timing": 2,
            "Action": 2,
            "Value": 50,
            "Wazano": 0
          },
          "ExtraAction2": {
            "Timing": 0,
            "Action": 0,
            "Value": 0,
            "Wazano": 0
          },
          "ExtraAction3": {
            "Timing": 0,
            "Action": 0,
            "Value": 0,
            "Wazano": 0
          },
          "ExtraAction4": {
            "Timing": 0,
            "Action": 0,
            "Value": 0,
            "Wazano": 0
          },
          "ExtraAction5": {
            "Timing": 0,
            "Action": 0,
            "Value": 0,
            "Wazano": 0
          },
          "ExtraAction6": {
            "Timing": 0,
            "Action": 0,
            "Value": 0,
            "Wazano": 0
          },
          "DoubleActionTriggerHp": 0,
          "DoubleActionTriggerTime": 0,
          "DoubleActionRate": 0
        },
        "TimeDesc": {
          "IsActive": false,
          "GameLimit": 0,
          "ClientLimit": 0,
          "CommandLimit": 0,
          "PokeReviveTime": 0,
          "AiIntervalTime": 0,
          "AiIntervalRand": 0
        }
      }
    },
    {
      "Info": {
        "RomVer": 0,
        "No": 13021,
        "DeliveryGroupID": 0,
        "Difficulty": 0,
        "Rate": 100,
        "DropTableFix": 8835431514330713714,
        "DropTableRandom": 8835431514330713714,
        "CaptureRate": 1,
        "CaptureLv": 35,
        "BossPokePara": {
          "DevId": 737,
          "FormId": 0,
          "Sex": 0,
          "Item": 0,
          "Level": 35,
          "BallId": 0,
          "WazaType": 1,
          "Waza1": {
            "WazaId": 44,
            "PointUp": 0
          },
          "Waza2": {
            "WazaId": 209,
            "PointUp": 0
          },
          "Waza3": {
            "WazaId": 435,
            "PointUp": 0
          },
          "Waza4": {
            "WazaId": 268,
            "PointUp": 0
          },
          "GemType": 1,
          "Seikaku": 0,
          "Tokusei": 1,
          "TalentType": 1,
          "TalentValue": {
            "HP": 0,
            "ATK": 0,
            "DEF": 0,
            "SPA": 0,
            "SPD": 0,
            "SPE": 0
          },
          "TalentVnum": 2,
          "EffortValue": {
            "HP": 0,
            "ATK": 0,
            "DEF": 0,
            "SPA": 0,
            "SPD": 0,
            "SPE": 0
          },
          "RareType": 0,
          "ScaleType": 0,
          "ScaleValue": 0
        },
        "BossPokeSize": {
          "HeightType": 0,
          "HeightValue": 0,
          "WeightType": 0,
          "WeightValue": 0,
          "ScaleType": 0,
          "ScaleValue": 0
        },
        "BossDesc": {
          "HpCoef": 800,
          "PowerChargeTrigerHp": 0,
          "PowerChargeTrigerTime": 0,
          "PowerChargeLimitTime": 0,
          "PowerChargeCancelDamage": 0,
          "PowerChargePenaltyTime": 0,
          "PowerChargePenaltyAction": 0,
          "PowerChargeDamageRate": 0,
          "PowerChargeGemDamageRate": 0,
          "PowerChargeChangeGemDamageRate": 0,
          "ExtraAction1": {
            "Timing": 2,
            "Action": 2,
            "Value": 50,
            "Wazano": 0
          },
          "ExtraAction2": {
            "Timing": 0,
            "Action": 0,
            "Value": 0,
            "Wazano": 0
          },
          "ExtraAction3": {
            "Timing": 0,
            "Action": 0,
            "Value": 0,
            "Wazano": 0
          },
          "ExtraAction4": {
            "Timing": 0,
            "Action": 0,
            "Value": 0,
            "Wazano": 0
          },
          "ExtraAction5": {
            "Timing": 0,
            "Action": 0,
            "Value": 0,
            "Wazano": 0
          },
          "ExtraAction6": {
            "Timing": 0,
            "Action": 0,
            "Value": 0,
            "Wazano": 0
          },
          "DoubleActionTriggerHp": 0,
          "DoubleActionTriggerTime": 0,
          "DoubleActionRate": 0
        },
        "TimeDesc": {
          "IsActive": false,
          "GameLimit": 0,
          "ClientLimit": 0,
          "CommandLimit": 0,
          "PokeReviveTime": 0,
          "AiIntervalTime": 0,
          "AiIntervalRand": 0
        }
      }
    },
    {
      "Info": {
        "RomVer": 0,
        "No": 13022,
        "DeliveryGroupID": 0,
        "Difficulty": 0,
        "Rate": 100,
        "DropTableFix": 8835428215795829081,
        "DropTableRandom": 8835428215795829081,
        "CaptureRate": 1,
        "CaptureLv": 35,
        "BossPokePara": {
          "DevId": 782,
          "FormId": 0,
          "Sex": 0,
          "Item": 0,
          "Level": 35,
          "BallId": 0,
          "WazaType": 1,
          "Waza1": {
            "WazaId": 29,
            "PointUp": 0
          },
          "Waza2": {
            "WazaId": 337,
            "PointUp": 0
          },
          "Waza3": {
            "WazaId": 568,
            "PointUp": 0
          },
          "Waza4": {
            "WazaId": 184,
            "PointUp": 0
          },
          "GemType": 1,
          "Seikaku": 0,
          "Tokusei": 1,
          "TalentType": 1,
          "TalentValue": {
            "HP": 0,
            "ATK": 0,
            "DEF": 0,
            "SPA": 0,
            "SPD": 0,
            "SPE": 0
          },
          "TalentVnum": 2,
          "EffortValue": {
            "HP": 0,
            "ATK": 0,
            "DEF": 0,
            "SPA": 0,
            "SPD": 0,
            "SPE": 0
          },
          "RareType": 0,
          "ScaleType": 0,
          "ScaleValue": 0
        },
        "BossPokeSize": {
          "HeightType": 0,
          "HeightValue": 0,
          "WeightType": 0,
          "WeightValue": 0,
          "ScaleType": 0,
          "ScaleValue": 0
        },
        "BossDesc": {
          "HpCoef": 800,
          "PowerChargeTrigerHp": 0,
          "PowerChargeTrigerTime": 0,
          "PowerChargeLimitTime": 0,
          "PowerChargeCancelDamage": 0,
          "PowerChargePenaltyTime": 0,
          "PowerChargePenaltyAction": 0,
          "PowerChargeDamageRate": 0,
          "PowerChargeGemDamageRate": 0,
          "PowerChargeChangeGemDamageRate": 0,
          "ExtraAction1": {
            "Timing": 2,
            "Action": 2,
            "Value": 50,
            "Wazano": 0
          },
          "ExtraAction2": {
            "Timing": 0,
            "Action": 0,
            "Value": 0,
            "Wazano": 0
          },
          "ExtraAction3": {
            "Timing": 0,
            "Action": 0,
            "Value": 0,
            "Wazano": 0
          },
          "ExtraAction4": {
            "Timing": 0,
            "Action": 0,
            "Value": 0,
            "Wazano": 0
          },
          "ExtraAction5": {
            "Timing": 0,
            "Action": 0,
            "Value": 0,
            "Wazano": 0
          },
          "ExtraAction6": {
            "Timing": 0,
            "Action": 0,
            "Value": 0,
            "Wazano": 0
          },
          "DoubleActionTriggerHp": 0,
          "DoubleActionTriggerTime": 0,
          "DoubleActionRate": 0
        },
        "TimeDesc": {
          "IsActive": false,
          "GameLimit": 0,
          "ClientLimit": 0,
          "CommandLimit": 0,
          "PokeReviveTime": 0,
          "AiIntervalTime": 0,
          "AiIntervalRand": 0
        }
      }
    },
    {
      "Info": {
        "RomVer": 0,
        "No": 13023,
        "DeliveryGroupID": 0,
        "Difficulty": 0,
        "Rate": 100,
        "DropTableFix": 8835428215795829081,
        "DropTableRandom": 8835428215795829081,
        "CaptureRate": 1,
        "CaptureLv": 35,
        "BossPokePara": {
          "DevId": 550,
          "FormId": 2,
          "Sex": 0,
          "Item": 0,
          "Level": 35,
          "BallId": 0,
          "WazaType": 1,
          "Waza1": {
            "WazaId": 453,
            "PointUp": 0
          },
          "Waza2": {
            "WazaId": 44,
            "PointUp": 0
          },
          "Waza3": {
            "WazaId": 29,
            "PointUp": 0
          },
          "Waza4": {
            "WazaId": 854,
            "PointUp": 0
          },
          "GemType": 1,
          "Seikaku": 0,
          "Tokusei": 1,
          "TalentType": 1,
          "TalentValue": {
            "HP": 0,
            "ATK": 0,
            "DEF": 0,
            "SPA": 0,
            "SPD": 0,
            "SPE": 0
          },
          "TalentVnum": 2,
          "EffortValue": {
            "HP": 0,
            "ATK": 0,
            "DEF": 0,
            "SPA": 0,
            "SPD": 0,
            "SPE": 0
          },
          "RareType": 0,
          "ScaleType": 0,
          "ScaleValue": 0
        },
        "BossPokeSize": {
          "HeightType": 0,
          "HeightValue": 0,
          "WeightType": 0,
          "WeightValue": 0,
          "ScaleType": 0,
          "ScaleValue": 0
        },
        "BossDesc": {
          "HpCoef": 800,
          "PowerChargeTrigerHp": 0,
          "PowerChargeTrigerTime": 0,
          "PowerChargeLimitTime": 0,
          "PowerChargeCancelDamage": 0,
          "PowerChargePenaltyTime": 0,
          "PowerChargePenaltyAction": 0,
          "PowerChargeDamageRate": 0,
          "PowerChargeGemDamageRate": 0,
          "PowerChargeChangeGemDamageRate": 0,
          "ExtraAction1": {
            "Timing": 2,
            "Action": 2,
            "Value": 50,
            "Wazano": 0
          },
          "ExtraAction2": {
            "Timing": 0,
            "Action": 0,
            "Value": 0,
            "Wazano": 0
          },
          "ExtraAction3": {
            "Timing": 0,
            "Action": 0,
            "Value": 0,
            "Wazano": 0
          },
          "ExtraAction4": {
            "Timing": 0,
            "Action": 0,
            "Value": 0,
            "Wazano": 0
          },
          "ExtraAction5": {
            "Timing": 0,
            "Action": 0,
            "Value": 0,
            "Wazano": 0
          },
          "ExtraAction6": {
            "Timing": 0,
            "Action": 0,
            "Value": 0,
            "Wazano": 0
          },
          "DoubleActionTriggerHp": 0,
          "DoubleActionTriggerTime": 0,
          "DoubleActionRate": 0
        },
        "TimeDesc": {
          "IsActive": false,
          "GameLimit": 0,
          "ClientLimit": 0,
          "CommandLimit": 0,
          "PokeReviveTime": 0,
          "AiIntervalTime": 0,
          "AiIntervalRand": 0
        }
      }
    },
    {
      "Info": {
        "RomVer": 0,
        "No": 13024,
        "DeliveryGroupID": 0,
        "Difficulty": 0,
        "Rate": 100,
        "DropTableFix": 8835431514330713714,
        "DropTableRandom": 8835431514330713714,
        "CaptureRate": 1,
        "CaptureLv": 35,
        "BossPokePara": {
          "DevId": 1024,
          "FormId": 0,
          "Sex": 0,
          "Item": 0,
          "Level": 35,
          "BallId": 0,
          "WazaType": 1,
          "Waza1": {
            "WazaId": 492,
            "PointUp": 0
          },
          "Waza2": {
            "WazaId": 72,
            "PointUp": 0
          },
          "Waza3": {
            "WazaId": 506,
            "PointUp": 0
          },
          "Waza4": {
            "WazaId": 71,
            "PointUp": 0
          },
          "GemType": 1,
          "Seikaku": 0,
          "Tokusei": 1,
          "TalentType": 1,
          "TalentValue": {
            "HP": 0,
            "ATK": 0,
            "DEF": 0,
            "SPA": 0,
            "SPD": 0,
            "SPE": 0
          },
          "TalentVnum": 2,
          "EffortValue": {
            "HP": 0,
            "ATK": 0,
            "DEF": 0,
            "SPA": 0,
            "SPD": 0,
            "SPE": 0
          },
          "RareType": 0,
          "ScaleType": 0,
          "ScaleValue": 0
        },
        "BossPokeSize": {
          "HeightType": 0,
          "HeightValue": 0,
          "WeightType": 0,
          "WeightValue": 0,
          "ScaleType": 0,
          "ScaleValue": 0
        },
        "BossDesc": {
          "HpCoef": 800,
          "PowerChargeTrigerHp": 0,
          "PowerChargeTrigerTime": 0,
          "PowerChargeLimitTime": 0,
          "PowerChargeCancelDamage": 0,
          "PowerChargePenaltyTime": 0,
          "PowerChargePenaltyAction": 0,
          "PowerChargeDamageRate": 0,
          "PowerChargeGemDamageRate": 0,
          "PowerChargeChangeGemDamageRate": 0,
          "ExtraAction1": {
            "Timing": 2,
            "Action": 2,
            "Value": 50,
            "Wazano": 0
          },
          "ExtraAction2": {
            "Timing": 0,
            "Action": 0,
            "Value": 0,
            "Wazano": 0
          },
          "ExtraAction3": {
            "Timing": 0,
            "Action": 0,
            "Value": 0,
            "Wazano": 0
          },
          "ExtraAction4": {
            "Timing": 0,
            "Action": 0,
            "Value": 0,
            "Wazano": 0
          },
          "ExtraAction5": {
            "Timing": 0,
            "Action": 0,
            "Value": 0,
            "Wazano": 0
          },
          "ExtraAction6": {
            "Timing": 0,
            "Action": 0,
            "Value": 0,
            "Wazano": 0
          },
          "DoubleActionTriggerHp": 0,
          "DoubleActionTriggerTime": 0,
          "DoubleActionRate": 0
        },
        "TimeDesc": {
          "IsActive": false,
          "GameLimit": 0,
          "ClientLimit": 0,
          "CommandLimit": 0,
          "PokeReviveTime": 0,
          "AiIntervalTime": 0,
          "AiIntervalRand": 0
        }
      }
    },
    {
      "Info": {
        "RomVer": 0,
        "No": 13025,
        "DeliveryGroupID": 0,
        "Difficulty": 0,
        "Rate": 100,
        "DropTableFix": 8835424917260944448,
        "DropTableRandom": 8835424917260944448,
        "CaptureRate": 1,
        "CaptureLv": 35,
        "BossPokePara": {
          "DevId": 840,
          "FormId": 0,
          "Sex": 0,
          "Item": 0,
          "Level": 35,
          "BallId": 0,
          "WazaType": 1,
          "Waza1": {
            "WazaId": 389,
            "PointUp": 0
          },
          "Waza2": {
            "WazaId": 110,
            "PointUp": 0
          },
          "Waza3": {
            "WazaId": 310,
            "PointUp": 0
          },
          "Waza4": {
            "WazaId": 0,
            "PointUp": 0
          },
          "GemType": 1,
          "Seikaku": 0,
          "Tokusei": 1,
          "TalentType": 1,
          "TalentValue": {
            "HP": 0,
            "ATK": 0,
            "DEF": 0,
            "SPA": 0,
            "SPD": 0,
            "SPE": 0
          },
          "TalentVnum": 2,
          "EffortValue": {
            "HP": 0,
            "ATK": 0,
            "DEF": 0,
            "SPA": 0,
            "SPD": 0,
            "SPE": 0
          },
          "RareType": 0,
          "ScaleType": 0,
          "ScaleValue": 0
        },
        "BossPokeSize": {
          "HeightType": 0,
          "HeightValue": 0,
          "WeightType": 0,
          "WeightValue": 0,
          "ScaleType": 0,
          "ScaleValue": 0
        },
        "BossDesc": {
          "HpCoef": 800,
          "PowerChargeTrigerHp": 0,
          "PowerChargeTrigerTime": 0,
          "PowerChargeLimitTime": 0,
          "PowerChargeCancelDamage": 0,
          "PowerChargePenaltyTime": 0,
          "PowerChargePenaltyAction": 0,
          "PowerChargeDamageRate": 0,
          "PowerChargeGemDamageRate": 0,
          "PowerChargeChangeGemDamageRate": 0,
          "ExtraAction1": {
            "Timing": 2,
            "Action": 2,
            "Value": 50,
            "Wazano": 0
          },
          "ExtraAction2": {
            "Timing": 0,
            "Action": 0,
            "Value": 0,
            "Wazano": 0
          },
          "ExtraAction3": {
            "Timing": 0,
            "Action": 0,
            "Value": 0,
            "Wazano": 0
          },
          "ExtraAction4": {
            "Timing": 0,
            "Action": 0,
            "Value": 0,
            "Wazano": 0
          },
          "ExtraAction5": {
            "Timing": 0,
            "Action": 0,
            "Value": 0,
            "Wazano": 0
          },
          "ExtraAction6": {
            "Timing": 0,
            "Action": 0,
            "Value": 0,
            "Wazano": 0
          },
          "DoubleActionTriggerHp": 0,
          "DoubleActionTriggerTime": 0,
          "DoubleActionRate": 0
        },
        "TimeDesc": {
          "IsActive": false,
          "GameLimit": 0,
          "ClientLimit": 0,
          "CommandLimit": 0,
          "PokeReviveTime": 0,
          "AiIntervalTime": 0,
          "AiIntervalRand": 0
        }
      }
    },
    {
      "Info": {
        "RomVer": 2,
        "No": 13026,
        "DeliveryGroupID": 0,
        "Difficulty": 0,
        "Rate": 100,
        "DropTableFix": 8835429315307457292,
        "DropTableRandom": 8835429315307457292,
        "CaptureRate": 1,
        "CaptureLv": 35,
        "BossPokePara": {
          "DevId": 190,
          "FormId": 0,
          "Sex": 0,
          "Item": 0,
          "Level": 35,
          "BallId": 0,
          "WazaType": 1,
          "Waza1": {
            "WazaId": 103,
            "PointUp": 0
          },
          "Waza2": {
            "WazaId": 154,
            "PointUp": 0
          },
          "Waza3": {
            "WazaId": 231,
            "PointUp": 0
          },
          "Waza4": {
            "WazaId": 21,
            "PointUp": 0
          },
          "GemType": 1,
          "Seikaku": 0,
          "Tokusei": 1,
          "TalentType": 1,
          "TalentValue": {
            "HP": 0,
            "ATK": 0,
            "DEF": 0,
            "SPA": 0,
            "SPD": 0,
            "SPE": 0
          },
          "TalentVnum": 2,
          "EffortValue": {
            "HP": 0,
            "ATK": 0,
            "DEF": 0,
            "SPA": 0,
            "SPD": 0,
            "SPE": 0
          },
          "RareType": 0,
          "ScaleType": 0,
          "ScaleValue": 0
        },
        "BossPokeSize": {
          "HeightType": 0,
          "HeightValue": 0,
          "WeightType": 0,
          "WeightValue": 0,
          "ScaleType": 0,
          "ScaleValue": 0
        },
        "BossDesc": {
          "HpCoef": 800,
          "PowerChargeTrigerHp": 0,
          "PowerChargeTrigerTime": 0,
          "PowerChargeLimitTime": 0,
          "PowerChargeCancelDamage": 0,
          "PowerChargePenaltyTime": 0,
          "PowerChargePenaltyAction": 0,
          "PowerChargeDamageRate": 0,
          "PowerChargeGemDamageRate": 0,
          "PowerChargeChangeGemDamageRate": 0,
          "ExtraAction1": {
            "Timing": 2,
            "Action": 2,
            "Value": 50,
            "Wazano": 0
          },
          "ExtraAction2": {
            "Timing": 0,
            "Action": 0,
            "Value": 0,
            "Wazano": 0
          },
          "ExtraAction3": {
            "Timing": 0,
            "Action": 0,
            "Value": 0,
            "Wazano": 0
          },
          "ExtraAction4": {
            "Timing": 0,
            "Action": 0,
            "Value": 0,
            "Wazano": 0
          },
          "ExtraAction5": {
            "Timing": 0,
            "Action": 0,
            "Value": 0,
            "Wazano": 0
          },
          "ExtraAction6": {
            "Timing": 0,
            "Action": 0,
            "Value": 0,
            "Wazano": 0
          },
          "DoubleActionTriggerHp": 0,
          "DoubleActionTriggerTime": 0,
          "DoubleActionRate": 0
        },
        "TimeDesc": {
          "IsActive": false,
          "GameLimit": 0,
          "ClientLimit": 0,
          "CommandLimit": 0,
          "PokeReviveTime": 0,
          "AiIntervalTime": 0,
          "AiIntervalRand": 0
        }
      }
    }
  ]
}